mkvimdb/__init__.py
mkvimdb/cli.py
mkvimdb/imdbops.py
mkvimdb/mkvimdb.py
mkvimdb/tagify.py
mkvimdb-0.2.3.dist-info/AUTHORS.rst
mkvimdb-0.2.3.dist-info/LICENSE
mkvimdb-0.2.3.dist-info/METADATA
mkvimdb-0.2.3.dist-info/WHEEL
mkvimdb-0.2.3.dist-info/entry_points.txt
mkvimdb-0.2.3.dist-info/top_level.txt
mkvimdb-0.2.3.dist-info/RECORD
