Metadata-Version: 2.1
Name: mkvimdb
Version: 0.2.3
Summary: Retag MKV files using IMDB, commandline, or an XML file.
Home-page: https://github.com/gnomonconquest/mkvimdb
Author: Dimitry Dukhovny
Author-email: gnomon@protonmail.com
License: MIT license
Keywords: mkvimdb
Platform: UNKNOWN
Classifier: Development Status :: 2 - Pre-Alpha
Classifier: Intended Audience :: Developers
Classifier: License :: OSI Approved :: MIT License
Classifier: Natural Language :: English
Classifier: Programming Language :: Python :: 3
Classifier: Programming Language :: Python :: 3.5
Classifier: Programming Language :: Python :: 3.6
Classifier: Programming Language :: Python :: 3.7
Classifier: Programming Language :: Python :: 3.8
Requires-Python: >=3.5
